{"app_common_office.md":"63a23693","guide_advanced_btrfs.md":"e5d12070","guide_advanced_debug.md":"34ee5c22","guide_advanced_make-install-disk.md":"3d0eab7d","guide_advanced_optional-cfg-1.md":"6c980b55","guide_advanced_optional-cfg-2.md":"a94669f9","guide_advanced_power-ctl.md":"b319d9f6","guide_advanced_system-ctl.md":"44aa2a9c","guide_index.md":"60d1af8a","guide_prepare_head-on-blow.md":"c045fddf","app_common_play.md":"7981a127","guide_rookie_basic-install.md":"b1df07fe","guide_rookie_desktop-env-and-app.md":"f1d0e239","guide_rookie_graphic-driver.md":"76f80494","guide_rookie_pre-install.md":"733ca5e7","guide_rookie_pre-virt.md":"15451e5b","guide_rookie_transparent.md":"c103f184","app_common_collaboration.md":"f5636724","app_common_communication.md":"1c0269e3","index.md":"1d98d5ec","guide_prepare_understand.md":"abf42080","app_common_daily.md":"1f6a09ea","app_common_media.md":"51e8a528","app_common_remote.md":"6ce86257","guide_rookie_basic-install-detail.md":"eea43409","app_exclusive_audio.md":"6f0a0646","app_exclusive_code.md":"5c39ae78","app_exclusive_image.md":"19ff430f","app_exclusive_media.md":"21a34c4c","app_common_android.md":"b4af4ea4","app_exclusive_video.md":"40f2cbc9","postscript_contribute.md":"f3a9ff59","postscript_contributor-covenant.md":"dbb166e9","postscript_copyright.md":"84133590","postscript_postscript.md":"3f2b2165","guide_advanced_beauty-3.md":"819c10b0","guide_advanced_beauty-1.md":"59404d40","guide_advanced_beauty-2.md":"d52ab929","postscript_about.md":"5707f0ef"}
